covidseverity/__init__.py
defend_covid_severity-0.1.4.dist-info/LICENSE
defend_covid_severity-0.1.4.dist-info/METADATA
defend_covid_severity-0.1.4.dist-info/WHEEL
defend_covid_severity-0.1.4.dist-info/top_level.txt
defend_covid_severity-0.1.4.dist-info/RECORD
