Metadata-Version: 2.1
Name: defend-covid-severity
Version: 0.1.4
Summary: Severity prediction views of the datasets provided by FAPESP COVID-19 DataSharing/BR
Home-page: https://defend-project.github.io/covid-severity
Author: Maria Gabriela Valeriano, Filipe Verri
Author-email: mariagabrielavaleriano@gmail.com, filipeverri@gmail.com
License: UNKNOWN
Project-URL: Bug Tracker, https://github.com/defend-project/covid-severity/issues
Platform: UNKNOWN
Classifier: Programming Language :: Python :: 3
Classifier: License :: OSI Approved :: MIT License
Classifier: Operating System :: OS Independent
Requires-Python: >=3.6
License-File: LICENSE
Requires-Dist: pandas (>=1.2.4)
Requires-Dist: numpy (>=1.20)
